flake8_json_reporter/__init__.py
flake8_json_reporter/reporters.py
flake8_json-24.4.0.dist-info/LICENSE
flake8_json-24.4.0.dist-info/METADATA
flake8_json-24.4.0.dist-info/WHEEL
flake8_json-24.4.0.dist-info/entry_points.txt
flake8_json-24.4.0.dist-info/top_level.txt
flake8_json-24.4.0.dist-info/RECORD
