Metadata-Version: 2.1
Name: flake8-json
Version: 24.4.0
Summary: JSON Formatting Reporter plugin for Flake8
Home-page: https://github.com/pycqa/flake8-json
Author: Ian Stapleton Cordasco
Author-email: graffatcolmingov@gmail.com
License: MIT
Classifier: Development Status :: 5 - Production/Stable
Classifier: Environment :: Console
Classifier: Framework :: Flake8
Classifier: Intended Audience :: Developers
Classifier: License :: OSI Approved :: MIT License
Classifier: Programming Language :: Python
Classifier: Programming Language :: Python :: 3
Classifier: Programming Language :: Python :: 3 :: Only
Classifier: Programming Language :: Python :: Implementation :: CPython
Classifier: Topic :: Software Development :: Quality Assurance
Requires-Python: >=3.6
License-File: LICENSE
